Cal77/__init__.py
Cal77-0.0.1.dist-info/METADATA
Cal77-0.0.1.dist-info/WHEEL
Cal77-0.0.1.dist-info/top_level.txt
Cal77-0.0.1.dist-info/RECORD
