Metadata-Version: 2.1
Name: Cal77
Version: 0.0.1
Summary: A python module which helps you make a calculator
Home-page: UNKNOWN
Author: Aadi77
Author-email: UNKNOWN
License: UNKNOWN
Keywords: python,Calculator,Cal77,Cal,cal77 ,cal
Platform: UNKNOWN
